hammadml/__init__.py
hammadml/data/__init__.py
hammadml/data/db.py
hammadml/data/vdb.py
hammadml/llms/__init__.py
hammadml/llms/claude.py
hammadml/llms/instruct.py
hammadml/text/__init__.py
hammadml/text/cross_encode.py
hammadml/text/loss.py
hammadml/text/semantic_search.py
hammadml/text/sentence_similarity.py
hammadml/text/util.py
hammadml-0.1.10.dist-info/METADATA
hammadml-0.1.10.dist-info/WHEEL
hammadml-0.1.10.dist-info/top_level.txt
hammadml-0.1.10.dist-info/RECORD
